programmers_dice/__init__.py
programmers_dice/__main__.py
programmers_dice/cli.py
programmers_dice/py.typed
programmers_dice-1.0.0.dist-info/LICENSE
programmers_dice-1.0.0.dist-info/METADATA
programmers_dice-1.0.0.dist-info/WHEEL
programmers_dice-1.0.0.dist-info/entry_points.txt
programmers_dice-1.0.0.dist-info/top_level.txt
programmers_dice-1.0.0.dist-info/RECORD
